twerk/__init__.py
twerk/__main__.py
twerk/cli.py
twerk/commands.py
twerk/gui.py
twerk/models.py
twerk/tests/__init__.py
twerk/tests/conftest.py
twerk/tests/test_models.py
twerk/utils.py
twerk/views/__init__.py
twerk/views/base.py
twerk/views/mixins.py
twerk/views/private.py
twerk/views/public.py
twerk-0.0.3.dist-info/entry_points.txt
twerk-0.0.3.dist-info/LICENSE.md
twerk-0.0.3.dist-info/WHEEL
twerk-0.0.3.dist-info/METADATA
twerk-0.0.3.dist-info/RECORD
