Metadata-Version: 2.1
Name: twerk
Version: 0.0.3
Summary: Make Twitter work for humans by blocking fake accounts.
Home-page: https://pypi.org/project/twerk
License: MIT
Author: Jace Browning
Author-email: jacebrowning@gmail.com
Requires-Python: >=3.7,<4.0
Classifier: Development Status :: 2 - Pre-Alpha
Classifier: Environment :: Console
Classifier: Environment :: Web Environment
Classifier: Framework :: Jupyter
Classifier: Intended Audience :: End Users/Desktop
Classifier: License :: OSI Approved :: MIT License
Classifier: Natural Language :: English
Classifier: Operating System :: OS Independent
Classifier: Programming Language :: Python
Classifier: Programming Language :: Python :: 3
Classifier: Programming Language :: Python :: 3.7
Classifier: Topic :: Communications
Classifier: Typing :: Typed
Requires-Dist: bullet (>=2.1.0,<3.0.0)
Requires-Dist: click (>=7.0,<8.0)
Requires-Dist: datafiles (>=0.5,<0.6)
Requires-Dist: ipdb (>=0.12.2,<0.13.0)
Requires-Dist: minilog (>=1.2.5,<2.0.0)
Requires-Dist: splinter (>=0.11.0,<0.12.0)
Requires-Dist: webdriver_manager (>=1.8.2,<2.0.0)
Project-URL: Documentation, https://twerk.readthedocs.io
Project-URL: Repository, https://github.com/jacebrowning/twerk
